sws_wrapper/Course.py
sws_wrapper/User.py
sws_wrapper/__init__.py
sws_wrapper/api.py
sws_wrapper-0.0.2.dist-info/METADATA
sws_wrapper-0.0.2.dist-info/WHEEL
sws_wrapper-0.0.2.dist-info/licenses/LICENSE.txt
sws_wrapper-0.0.2.dist-info/RECORD
