Metadata-Version: 2.1
Name: sws_wrapper
Version: 0.0.2
Summary: An API wrapper for So We Sign
License:             DO WHAT THE FUCK YOU WANT TO PUBLIC LICENSE
License-File: LICENSE.txt
Classifier: License :: OSI Approved :: MIT License
Classifier: Programming Language :: Python :: 3
Requires-Python: >=3.8
Requires-Dist: user-agent
